random_test/__init__.py
random_test/random.py
highly_random_test-0.1.2.dist-info/METADATA
highly_random_test-0.1.2.dist-info/WHEEL
highly_random_test-0.1.2.dist-info/licenses/LICENSE
highly_random_test-0.1.2.dist-info/RECORD
