Metadata-Version: 2.3
Name: highly-random-test
Version: 0.1.2
Summary: An random test project for publishing.
Author-email: Quirky-AI-Labs <quirkyailabs@gmail.com>
License: MIT License
License-File: LICENSE
Keywords: random,random-test,test
Requires-Python: >=3.8
